perika/__init__.py
perika/clock.py
perika/flow.py
perika/main.py
perika/engine/__init__.py
perika/engine/base.py
perika/engine/faker.py
perika/engine/fishtext.py
perika/engine/gigachat.py
perika/game/__init__.py
perika/game/choises.py
perika/game/level.py
perika/game/player.py
perika/game/rule.py
perika/game/score.py
perika/game/task.py
perika/game/text.py
perika_game-0.1.0.dist-info/METADATA
perika_game-0.1.0.dist-info/WHEEL
perika_game-0.1.0.dist-info/entry_points.txt
perika_game-0.1.0.dist-info/RECORD
