Metadata-Version: 2.3
Name: perika-game
Version: 0.1.0
Summary: Simple console game, for training rapid typing in you favorite shell.
Author-email: Arsen Gumin <gumin@live.ru>
License-Expression: MIT
Requires-Python: >=3.9
Requires-Dist: requests>=2.32.3
Requires-Dist: rich>=13.7.1
Requires-Dist: typer>=0.12.3
